<strings>
  <string key="WORKSHOP_HLP">
    Мастерская предмета определяет принадлежность предмета к определенной категории. Вы можете устанавливать оружие и модули на корабль только от вашей мастерской
  </string>
  <string key="LAD_HLP">
    Урон от обычной атаки, не требующей затрат энергии
  </string>
  <string key="LAC_HLP">
    Кулдаун обычной атаки
  </string>
  <string key="LACD_HLP">
    Критический урон от обычной атаки
  </string>
  <string key="HAD_HLP">
    Урон от усиленной атаки, требующий затрат энергии и имеющий больший кулдаун, чем обычная атака. Используются для нанесения усиленного урона врагу.
  </string>
  <string key="HAC_HLP">
    Кулдаун усиленной атаки
  </string>
  <string key="HACD_HLP">
    Критический урон от усилиенной атаки
  </string>
  <string key="HAE_HLP">
    При использовании усиленной атаки тратится энергия корабля, которая затем медленно восстанавливается со временем
  </string>
  <string key="CC_HLP">
    Вероятность критического урона - шанс нансения критического урона при атаке. Этот шанс общий для обычных и тяжелых атак
  </string>
  <string key="OD_HLP">
    Оптимальное расстояние - рсстояние, на которое надо подлететь к врагу, чтобы вероятность попадания по цели стала максимальной
  </string>
  <string key="R_HLP">
    Диапазон определяет насколько быстро увеличивается вероятность попадания по цели. Это расстояние, которое нужно пролететь, чтобы вероятность попадания по цели увеличила от 0% до максимальной
  </string>
</strings>